tree_sitter_paradox/__init__.py
tree_sitter_paradox/__init__.pyi
tree_sitter_paradox/_binding.pyd
tree_sitter_paradox/binding.c
tree_sitter_paradox/py.typed
tree_sitter_paradox/queries/highlights.scm
tree_sitter_paradox-0.2.0.dist-info/licenses/LICENSE
tree_sitter_paradox-0.2.0.dist-info/METADATA
tree_sitter_paradox-0.2.0.dist-info/WHEEL
tree_sitter_paradox-0.2.0.dist-info/top_level.txt
tree_sitter_paradox-0.2.0.dist-info/RECORD
