Metadata-Version: 2.4
Name: tree-sitter-paradox
Version: 0.2.0
Summary: Paradox grammar for tree-sitter
Author-email: acture <acturea@gmail.com>
License: AGPL-3.0-only
Project-URL: Homepage, https://github.com/acture/tree-sitter-paradox.git
Keywords: incremental,parsing,tree-sitter,paradox
Classifier: Intended Audience :: Developers
Classifier: Topic :: Software Development :: Compilers
Classifier: Topic :: Text Processing :: Linguistic
Classifier: Typing :: Typed
Requires-Python: >=3.10
License-File: LICENSE
Provides-Extra: core
Requires-Dist: tree-sitter~=0.24; extra == "core"
Dynamic: license-file
